setup.cfg
setup.py
simple_sms_forms.egg-info/PKG-INFO
simple_sms_forms.egg-info/SOURCES.txt
simple_sms_forms.egg-info/dependency_links.txt
simple_sms_forms.egg-info/entry_points.txt
simple_sms_forms.egg-info/top_level.txt
simple_sms_forms.egg-info/zip-safe
simplesmsforms/__init__.py
simplesmsforms/smsform.py
simplesmsforms/smsform_exceptions.py
simplesmsforms/smsform_fields.py
simplesmsforms/smsform_validators.py
simplesmsforms/smstests.py