Metadata-Version: 1.0
Name: simple-sms-forms
Version: 0.3.1b
Summary: Simple SMS text processor for Django/Rapidsms
Home-page: https://github.com/AndreLesa/simplesmsforms
Author: Andre Lesa
Author-email: andre@andrelesa.com
License: MIT
Keywords: RapidSMS,SMS,Django
Platform: UNKNOWN
